ilcs_parser/__init__.py
ilcs_parser/learned_settings.crfsuite
ilcs_parser-0.1.0.dist-info/LICENSE
ilcs_parser-0.1.0.dist-info/METADATA
ilcs_parser-0.1.0.dist-info/WHEEL
ilcs_parser-0.1.0.dist-info/top_level.txt
ilcs_parser-0.1.0.dist-info/RECORD
